kbanksdk/__init__.py
kbanksdk/createCharge.py
kbanksdk/exceptions.py
kbanksdk/inquire_card.py
kbanksdk/kivDataclass.py
kbanksdk/payment.py
kbanksdk/version.py
kbanksdk-0.2.0.dist-info/LICENSE
kbanksdk-0.2.0.dist-info/METADATA
kbanksdk-0.2.0.dist-info/WHEEL
kbanksdk-0.2.0.dist-info/top_level.txt
kbanksdk-0.2.0.dist-info/RECORD
