Metadata-Version: 2.1
Name: kbanksdk
Version: 0.2.0
Summary: KBank Payment Gateway SDK for Python
Home-page: https://github.com/villa-market/kbanksdk
Author: nic wanavit
Author-email: nwanavit@hatari.cc
Classifier: Programming Language :: Python :: 3
Classifier: License :: OSI Approved :: MIT License
Classifier: Operating System :: OS Independent
Requires-Python: >=3.10
License-File: LICENSE
Requires-Dist: requests>=2.25.1
Requires-Dist: pydantic>=2.6.1
Requires-Dist: dataclasses-json>=0.5.7
